LICENSE
README.md
setup.py
parseq/CODERULES.txt
parseq/__init__.py
parseq/description.py
parseq/version.py
parseq.egg-info/PKG-INFO
parseq.egg-info/SOURCES.txt
parseq.egg-info/dependency_links.txt
parseq.egg-info/not-zip-safe
parseq.egg-info/requires.txt
parseq.egg-info/top_level.txt
parseq/core/__init__.py
parseq/core/commons.py
parseq/core/config.py
parseq/core/correction.py
parseq/core/logger.py
parseq/core/nodes.py
parseq/core/plotExport.py
parseq/core/save_restore.py
parseq/core/singletons.py
parseq/core/spectra.py
parseq/core/transforms.py
parseq/fits/__init__.py
parseq/fits/basefit.py
parseq/fits/exafsfit.py
parseq/fits/functionfit.py
parseq/fits/lcf.py
parseq/gui/__init__.py
parseq/gui/aboutDialog.py
parseq/gui/calibrateEnergy.py
parseq/gui/columnFormat.py
parseq/gui/combineSpectra.py
parseq/gui/dataRebin.py
parseq/gui/dataTreeModelView.py
parseq/gui/fileDialogs.py
parseq/gui/fileTreeModelView.py
parseq/gui/gcommons.py
parseq/gui/gcorrection.py
parseq/gui/glitches.py
parseq/gui/mainWindow.py
parseq/gui/nodeWidget.py
parseq/gui/plot.py
parseq/gui/plotOptions.py
parseq/gui/propWidget.py
parseq/gui/propsOfData.py
parseq/gui/roi.py
parseq/gui/tasker.py
parseq/gui/undoredo.py
parseq/gui/webWidget.py
parseq/gui/_images/icon-add-correction-delete-24.png
parseq/gui/_images/icon-add-correction-delete-32.png
parseq/gui/_images/icon-add-correction-delete-64.png
parseq/gui/_images/icon-add-correction-scale-24.png
parseq/gui/_images/icon-add-correction-scale-32.png
parseq/gui/_images/icon-add-correction-scale-64.png
parseq/gui/_images/icon-add-correction-spikes-24.png
parseq/gui/_images/icon-add-correction-spikes-32.png
parseq/gui/_images/icon-add-correction-spikes-64.png
parseq/gui/_images/icon-add-correction-spline--24.png
parseq/gui/_images/icon-add-correction-spline--32.png
parseq/gui/_images/icon-add-correction-spline--64.png
parseq/gui/_images/icon-add-correction-spline-24.png
parseq/gui/_images/icon-add-correction-spline-32.png
parseq/gui/_images/icon-add-correction-spline-64.png
parseq/gui/_images/icon-add-correction-step-24.png
parseq/gui/_images/icon-add-correction-step-32.png
parseq/gui/_images/icon-add-correction-step-64.png
