Metadata-Version: 2.4
Name: parseq
Version: 2026.1.0
Summary: ParSeq is a python software library for Parallel execution of Sequential data analysis.
Home-page: http://parseq.readthedocs.io
Author: Konstantin Klementiev
Author-email: konstantin.klementiev@gmail.com
License: MIT
Project-URL: Source, https://github.com/kklmn/ParSeq
Keywords: data-analysis pipeline framework gui synchrotron spectroscopy
Platform: OS Independent
Classifier: Development Status :: 5 - Production/Stable
Classifier: Intended Audience :: Science/Research
Classifier: Natural Language :: English
Classifier: Operating System :: OS Independent
Classifier: Programming Language :: Python
Classifier: Intended Audience :: Science/Research
Classifier: Topic :: Scientific/Engineering
Classifier: Topic :: Software Development
Classifier: Topic :: Software Development :: User Interfaces
License-File: LICENSE
Requires-Dist: numpy>=1.8.0
Requires-Dist: scipy>=0.17.0
Requires-Dist: matplotlib>=2.0.0
Requires-Dist: sphinx>=1.6.2
Requires-Dist: sphinxcontrib-jquery
Requires-Dist: autopep8
Requires-Dist: h5py
Requires-Dist: silx>=1.1.0
Requires-Dist: hdf5plugin
Requires-Dist: psutil
Requires-Dist: pyqtwebengine
Requires-Dist: docutils
Requires-Dist: distro
Requires-Dist: colorama
Requires-Dist: sphinx_tabs
Requires-Dist: xafsmass>=1.6.0
Dynamic: author
Dynamic: author-email
Dynamic: classifier
Dynamic: description
Dynamic: description-content-type
Dynamic: home-page
Dynamic: keywords
Dynamic: license
Dynamic: license-file
Dynamic: platform
Dynamic: project-url
Dynamic: requires-dist
Dynamic: summary
